pyshotgrid/__init__.py
pyshotgrid/core.py
pyshotgrid/sg_default_entities.py
pyshotgrid-2.1.0.dist-info/licenses/LICENSE
pyshotgrid-2.1.0.dist-info/METADATA
pyshotgrid-2.1.0.dist-info/WHEEL
pyshotgrid-2.1.0.dist-info/top_level.txt
pyshotgrid-2.1.0.dist-info/RECORD
