Metadata-Version: 2.4
Name: pyshotgrid
Version: 2.1.0
Summary: A pythonic and object oriented way to talk to Autodesk ShotGrid.
Author-email: Fabian Geisler <info@fasbue.com>
License: MIT
Project-URL: Homepage, https://github.com/fabiangeisler/pyshotgrid
Project-URL: Documentation, https://fabiangeisler.github.io/pyshotgrid
Project-URL: Bug Tracker, https://github.com/fabiangeisler/pyshotgrid/issues
Keywords: shotgrid
Classifier: Development Status :: 5 - Production/Stable
Classifier: Intended Audience :: Developers
Classifier: License :: OSI Approved :: MIT License
Classifier: Natural Language :: English
Classifier: Programming Language :: Python :: 3
Classifier: Programming Language :: Python :: 3.9
Classifier: Programming Language :: Python :: 3.10
Classifier: Programming Language :: Python :: 3.11
Classifier: Programming Language :: Python :: 3.12
Classifier: Operating System :: OS Independent
Requires-Python: >=3.9
License-File: LICENSE
Requires-Dist: shotgun-api3>=3.9.2
Dynamic: license-file
